causal_ccm/__init__.py
causal_ccm/causal_ccm.py
causal_ccm-0.3.2.dist-info/LICENSE
causal_ccm-0.3.2.dist-info/METADATA
causal_ccm-0.3.2.dist-info/WHEEL
causal_ccm-0.3.2.dist-info/top_level.txt
causal_ccm-0.3.2.dist-info/RECORD
