Metadata-Version: 2.1
Name: causal-ccm
Version: 0.3.2
Summary: implementation of convergent cross mapping by Sugihara et al (2012)
Home-page: https://github.com/PrinceJavier/causal_ccm
Author: Prince Javier
Author-email: othepjavier@gmail.com
License: MIT
Download-URL: https://github.com/PrinceJavier/causal_ccm/archive/v_03.tar.gz
Keywords: causality,dynamical systems,complex systems
Platform: UNKNOWN
Classifier: Development Status :: 3 - Alpha
Classifier: Intended Audience :: Developers
Classifier: Topic :: Software Development :: Build Tools
Classifier: License :: OSI Approved :: MIT License
Classifier: Programming Language :: Python :: 3
Classifier: Programming Language :: Python :: 3.4
Classifier: Programming Language :: Python :: 3.5
Classifier: Programming Language :: Python :: 3.6
Requires-Dist: numpy
Requires-Dist: pandas
Requires-Dist: matplotlib
Requires-Dist: seaborn
Requires-Dist: scipy
